midas/tools/analysis/__init__.py
midas/tools/analysis/analysis.py
midas/tools/analysis/bus_analysis.py
midas/tools/analysis/power_analysis.py
midas_analysis-1.0.0rc2.dist-info/LICENSE
midas_analysis-1.0.0rc2.dist-info/METADATA
midas_analysis-1.0.0rc2.dist-info/WHEEL
midas_analysis-1.0.0rc2.dist-info/top_level.txt
midas_analysis-1.0.0rc2.dist-info/RECORD
